ZinckLib/__init__.py
ZinckLib/isAlphabetical.py
ZinckLib/morseToChar.py
ZinckLib/numberToText.py
ZinckLib/primeList.py
ZinckLib/splitString.py
ZinckLib/stringToPhonetic.py
ZinckLib/toLetter.py
ZinckLib/toNumber.py
ZinckLib-0.2.0.dist-info/LICENSE
ZinckLib-0.2.0.dist-info/METADATA
ZinckLib-0.2.0.dist-info/WHEEL
ZinckLib-0.2.0.dist-info/top_level.txt
ZinckLib-0.2.0.dist-info/RECORD
