Metadata-Version: 2.1
Name: ZinckLib
Version: 0.2.0
Summary: A small package of a bunch of functions I made, I hope you like it
Home-page: https://github.com/Zinckle/ZinckLib
Author: Mitchell Zinck
Author-email: mzinck9@gmail.com
Project-URL: Bug Tracker, https://github.com/Zinckle/ZinckLib/issues
Classifier: Programming Language :: Python :: 3
Classifier: License :: OSI Approved :: MIT License
Classifier: Operating System :: OS Independent
Requires-Python: >=3.10
License-File: LICENSE
